sniff/__init__.py
libsniff.cpython-39-x86_64-linux-gnu.so
libsniffpy-0.3.2.dist-info/COPYING
libsniffpy-0.3.2.dist-info/WHEEL
libsniffpy-0.3.2.dist-info/METADATA
libsniffpy-0.3.2.dist-info/RECORD
