Metadata-Version: 2.1
Name: libsniffpy
Version: 0.3.2
Summary: A python3 wrapper around libsniff
Home-page: https://github.com/4thel00z/libsniffpy
License: GPL-3
Author: 4thel00z
Author-email: 4thel00z@gmail.com
Requires-Python: >=3.7,<4.0
Classifier: License :: Other/Proprietary License
Classifier: Programming Language :: Python :: 3
Classifier: Programming Language :: Python :: 3.7
Classifier: Programming Language :: Python :: 3.8
Classifier: Programming Language :: Python :: 3.9
Requires-Dist: Cython (>=0.29.24,<0.30.0)
Requires-Dist: dpkt (>=1.9.6,<2.0.0)
